{"nodes": [{"id": "d_hms_project_backend_app_api_v1_endpoints_auth_py", "label": "auth.py", "file_type": "code", "source_file": "D:\\hms-project\\backend\\app\\api\\v1\\endpoints\\auth.py", "source_location": "L1"}, {"id": "auth_find_user_by_login", "label": "_find_user_by_login()", "file_type": "code", "source_file": "D:\\hms-project\\backend\\app\\api\\v1\\endpoints\\auth.py", "source_location": "L22"}, {"id": "auth_login", "label": "login()", "file_type": "code", "source_file": "D:\\hms-project\\backend\\app\\api\\v1\\endpoints\\auth.py", "source_location": "L45"}, {"id": "auth_logout", "label": "logout()", "file_type": "code", "source_file": "D:\\hms-project\\backend\\app\\api\\v1\\endpoints\\auth.py", "source_location": "L79"}, {"id": "auth_passwordresetrequest", "label": "PasswordResetRequest", "file_type": "code", "source_file": "D:\\hms-project\\backend\\app\\api\\v1\\endpoints\\auth.py", "source_location": "L109"}, {"id": "basemodel", "label": "BaseModel", "file_type": "code", "source_file": "", "source_location": ""}, {"id": "auth_passwordresetconfirm", "label": "PasswordResetConfirm", "file_type": "code", "source_file": "D:\\hms-project\\backend\\app\\api\\v1\\endpoints\\auth.py", "source_location": "L112"}, {"id": "auth_request_password_reset", "label": "request_password_reset()", "file_type": "code", "source_file": "D:\\hms-project\\backend\\app\\api\\v1\\endpoints\\auth.py", "source_location": "L118"}, {"id": "auth_confirm_password_reset", "label": "confirm_password_reset()", "file_type": "code", "source_file": "D:\\hms-project\\backend\\app\\api\\v1\\endpoints\\auth.py", "source_location": "L151"}, {"id": "auth_rationale_23", "label": "Find user by email OR by doctor employee_id.     identifier is lowercased before", "file_type": "rationale", "source_file": "D:\\hms-project\\backend\\app\\api\\v1\\endpoints\\auth.py", "source_location": "L23"}, {"id": "auth_rationale_46", "label": "Login with email OR employee_id (for doctors) + password.     Returns JWT token", "file_type": "rationale", "source_file": "D:\\hms-project\\backend\\app\\api\\v1\\endpoints\\auth.py", "source_location": "L46"}, {"id": "auth_rationale_83", "label": "Revokes the current JWT token by adding it to the blacklist.     Required for HI", "file_type": "rationale", "source_file": "D:\\hms-project\\backend\\app\\api\\v1\\endpoints\\auth.py", "source_location": "L83"}, {"id": "auth_rationale_119", "label": "Step 1: Generate OTP and send via email.", "file_type": "rationale", "source_file": "D:\\hms-project\\backend\\app\\api\\v1\\endpoints\\auth.py", "source_location": "L119"}, {"id": "auth_rationale_152", "label": "Step 2: Verify OTP and update password.", "file_type": "rationale", "source_file": "D:\\hms-project\\backend\\app\\api\\v1\\endpoints\\auth.py", "source_location": "L152"}], "edges": [{"source": "d_hms_project_backend_app_api_v1_endpoints_auth_py", "target": "logging", "relation": "imports", "confidence": "EXTRACTED", "source_file": "D:\\hms-project\\backend\\app\\api\\v1\\endpoints\\auth.py", "source_location": "L1", "weight": 1.0}, {"source": "d_hms_project_backend_app_api_v1_endpoints_auth_py", "target": "random", "relation": "imports", "confidence": "EXTRACTED", "source_file": "D:\\hms-project\\backend\\app\\api\\v1\\endpoints\\auth.py", "source_location": "L2", "weight": 1.0}, {"source": "d_hms_project_backend_app_api_v1_endpoints_auth_py", "target": "datetime", "relation": "imports_from", "confidence": "EXTRACTED", "source_file": "D:\\hms-project\\backend\\app\\api\\v1\\endpoints\\auth.py", "source_location": "L3", "weight": 1.0}, {"source": "d_hms_project_backend_app_api_v1_endpoints_auth_py", "target": "fastapi", "relation": "imports_from", "confidence": "EXTRACTED", "source_file": "D:\\hms-project\\backend\\app\\api\\v1\\endpoints\\auth.py", "source_location": "L4", "weight": 1.0}, {"source": "d_hms_project_backend_app_api_v1_endpoints_auth_py", "target": "fastapi_security", "relation": "imports_from", "confidence": "EXTRACTED", "source_file": "D:\\hms-project\\backend\\app\\api\\v1\\endpoints\\auth.py", "source_location": "L5", "weight": 1.0}, {"source": "d_hms_project_backend_app_api_v1_endpoints_auth_py", "target": "sqlalchemy_orm", "relation": "imports_from", "confidence": "EXTRACTED", "source_file": "D:\\hms-project\\backend\\app\\api\\v1\\endpoints\\auth.py", "source_location": "L6", "weight": 1.0}, {"source": "d_hms_project_backend_app_api_v1_endpoints_auth_py", "target": "pydantic", "relation": "imports_from", "confidence": "EXTRACTED", "source_file": "D:\\hms-project\\backend\\app\\api\\v1\\endpoints\\auth.py", "source_location": "L7", "weight": 1.0}, {"source": "d_hms_project_backend_app_api_v1_endpoints_auth_py", "target": "app_db_database", "relation": "imports_from", "confidence": "EXTRACTED", "source_file": "D:\\hms-project\\backend\\app\\api\\v1\\endpoints\\auth.py", "source_location": "L8", "weight": 1.0}, {"source": "d_hms_project_backend_app_api_v1_endpoints_auth_py", "target": "app_core_security", "relation": "imports_from", "confidence": "EXTRACTED", "source_file": "D:\\hms-project\\backend\\app\\api\\v1\\endpoints\\auth.py", "source_location": "L9", "weight": 1.0}, {"source": "d_hms_project_backend_app_api_v1_endpoints_auth_py", "target": "app_core_encryption", "relation": "imports_from", "confidence": "EXTRACTED", "source_file": "D:\\hms-project\\backend\\app\\api\\v1\\endpoints\\auth.py", "source_location": "L10", "weight": 1.0}, {"source": "d_hms_project_backend_app_api_v1_endpoints_auth_py", "target": "app_core_deps", "relation": "imports_from", "confidence": "EXTRACTED", "source_file": "D:\\hms-project\\backend\\app\\api\\v1\\endpoints\\auth.py", "source_location": "L11", "weight": 1.0}, {"source": "d_hms_project_backend_app_api_v1_endpoints_auth_py", "target": "app_core_email", "relation": "imports_from", "confidence": "EXTRACTED", "source_file": "D:\\hms-project\\backend\\app\\api\\v1\\endpoints\\auth.py", "source_location": "L12", "weight": 1.0}, {"source": "d_hms_project_backend_app_api_v1_endpoints_auth_py", "target": "app_models_user", "relation": "imports_from", "confidence": "EXTRACTED", "source_file": "D:\\hms-project\\backend\\app\\api\\v1\\endpoints\\auth.py", "source_location": "L13", "weight": 1.0}, {"source": "d_hms_project_backend_app_api_v1_endpoints_auth_py", "target": "app_models_security", "relation": "imports_from", "confidence": "EXTRACTED", "source_file": "D:\\hms-project\\backend\\app\\api\\v1\\endpoints\\auth.py", "source_location": "L14", "weight": 1.0}, {"source": "d_hms_project_backend_app_api_v1_endpoints_auth_py", "target": "app_models_otp", "relation": "imports_from", "confidence": "EXTRACTED", "source_file": "D:\\hms-project\\backend\\app\\api\\v1\\endpoints\\auth.py", "source_location": "L15", "weight": 1.0}, {"source": "d_hms_project_backend_app_api_v1_endpoints_auth_py", "target": "app_models_doctor", "relation": "imports_from", "confidence": "EXTRACTED", "source_file": "D:\\hms-project\\backend\\app\\api\\v1\\endpoints\\auth.py", "source_location": "L16", "weight": 1.0}, {"source": "d_hms_project_backend_app_api_v1_endpoints_auth_py", "target": "auth_find_user_by_login", "relation": "contains", "confidence": "EXTRACTED", "source_file": "D:\\hms-project\\backend\\app\\api\\v1\\endpoints\\auth.py", "source_location": "L22", "weight": 1.0}, {"source": "d_hms_project_backend_app_api_v1_endpoints_auth_py", "target": "auth_login", "relation": "contains", "confidence": "EXTRACTED", "source_file": "D:\\hms-project\\backend\\app\\api\\v1\\endpoints\\auth.py", "source_location": "L45", "weight": 1.0}, {"source": "d_hms_project_backend_app_api_v1_endpoints_auth_py", "target": "auth_logout", "relation": "contains", "confidence": "EXTRACTED", "source_file": "D:\\hms-project\\backend\\app\\api\\v1\\endpoints\\auth.py", "source_location": "L79", "weight": 1.0}, {"source": "d_hms_project_backend_app_api_v1_endpoints_auth_py", "target": "auth_passwordresetrequest", "relation": "contains", "confidence": "EXTRACTED", "source_file": "D:\\hms-project\\backend\\app\\api\\v1\\endpoints\\auth.py", "source_location": "L109", "weight": 1.0}, {"source": "auth_passwordresetrequest", "target": "basemodel", "relation": "inherits", "confidence": "EXTRACTED", "source_file": "D:\\hms-project\\backend\\app\\api\\v1\\endpoints\\auth.py", "source_location": "L109", "weight": 1.0}, {"source": "d_hms_project_backend_app_api_v1_endpoints_auth_py", "target": "auth_passwordresetconfirm", "relation": "contains", "confidence": "EXTRACTED", "source_file": "D:\\hms-project\\backend\\app\\api\\v1\\endpoints\\auth.py", "source_location": "L112", "weight": 1.0}, {"source": "auth_passwordresetconfirm", "target": "basemodel", "relation": "inherits", "confidence": "EXTRACTED", "source_file": "D:\\hms-project\\backend\\app\\api\\v1\\endpoints\\auth.py", "source_location": "L112", "weight": 1.0}, {"source": "d_hms_project_backend_app_api_v1_endpoints_auth_py", "target": "auth_request_password_reset", "relation": "contains", "confidence": "EXTRACTED", "source_file": "D:\\hms-project\\backend\\app\\api\\v1\\endpoints\\auth.py", "source_location": "L118", "weight": 1.0}, {"source": "d_hms_project_backend_app_api_v1_endpoints_auth_py", "target": "auth_confirm_password_reset", "relation": "contains", "confidence": "EXTRACTED", "source_file": "D:\\hms-project\\backend\\app\\api\\v1\\endpoints\\auth.py", "source_location": "L151", "weight": 1.0}, {"source": "auth_login", "target": "auth_find_user_by_login", "relation": "calls", "confidence": "EXTRACTED", "source_file": "D:\\hms-project\\backend\\app\\api\\v1\\endpoints\\auth.py", "source_location": "L50", "weight": 1.0}, {"source": "auth_rationale_23", "target": "auth_find_user_by_login", "relation": "rationale_for", "confidence": "EXTRACTED", "source_file": "D:\\hms-project\\backend\\app\\api\\v1\\endpoints\\auth.py", "source_location": "L23", "weight": 1.0}, {"source": "auth_rationale_46", "target": "auth_login", "relation": "rationale_for", "confidence": "EXTRACTED", "source_file": "D:\\hms-project\\backend\\app\\api\\v1\\endpoints\\auth.py", "source_location": "L46", "weight": 1.0}, {"source": "auth_rationale_83", "target": "auth_logout", "relation": "rationale_for", "confidence": "EXTRACTED", "source_file": "D:\\hms-project\\backend\\app\\api\\v1\\endpoints\\auth.py", "source_location": "L83", "weight": 1.0}, {"source": "auth_rationale_119", "target": "auth_request_password_reset", "relation": "rationale_for", "confidence": "EXTRACTED", "source_file": "D:\\hms-project\\backend\\app\\api\\v1\\endpoints\\auth.py", "source_location": "L119", "weight": 1.0}, {"source": "auth_rationale_152", "target": "auth_confirm_password_reset", "relation": "rationale_for", "confidence": "EXTRACTED", "source_file": "D:\\hms-project\\backend\\app\\api\\v1\\endpoints\\auth.py", "source_location": "L152", "weight": 1.0}], "raw_calls": [{"caller_nid": "auth_find_user_by_login", "callee": "strip", "source_file": "D:\\hms-project\\backend\\app\\api\\v1\\endpoints\\auth.py", "source_location": "L27"}, {"caller_nid": "auth_find_user_by_login", "callee": "lower", "source_file": "D:\\hms-project\\backend\\app\\api\\v1\\endpoints\\auth.py", "source_location": "L27"}, {"caller_nid": "auth_find_user_by_login", "callee": "first", "source_file": "D:\\hms-project\\backend\\app\\api\\v1\\endpoints\\auth.py", "source_location": "L30"}, {"caller_nid": "auth_find_user_by_login", "callee": "filter", "source_file": "D:\\hms-project\\backend\\app\\api\\v1\\endpoints\\auth.py", "source_location": "L30"}, {"caller_nid": "auth_find_user_by_login", "callee": "query", "source_file": "D:\\hms-project\\backend\\app\\api\\v1\\endpoints\\auth.py", "source_location": "L30"}, {"caller_nid": "auth_find_user_by_login", "callee": "get_blind_index", "source_file": "D:\\hms-project\\backend\\app\\api\\v1\\endpoints\\auth.py", "source_location": "L30"}, {"caller_nid": "auth_find_user_by_login", "callee": "upper", "source_file": "D:\\hms-project\\backend\\app\\api\\v1\\endpoints\\auth.py", "source_location": "L36"}, {"caller_nid": "auth_find_user_by_login", "callee": "first", "source_file": "D:\\hms-project\\backend\\app\\api\\v1\\endpoints\\auth.py", "source_location": "L37"}, {"caller_nid": "auth_find_user_by_login", "callee": "filter", "source_file": "D:\\hms-project\\backend\\app\\api\\v1\\endpoints\\auth.py", "source_location": "L37"}, {"caller_nid": "auth_find_user_by_login", "callee": "query", "source_file": "D:\\hms-project\\backend\\app\\api\\v1\\endpoints\\auth.py", "source_location": "L37"}, {"caller_nid": "auth_login", "callee": "verify_password", "source_file": "D:\\hms-project\\backend\\app\\api\\v1\\endpoints\\auth.py", "source_location": "L52"}, {"caller_nid": "auth_login", "callee": "HTTPException", "source_file": "D:\\hms-project\\backend\\app\\api\\v1\\endpoints\\auth.py", "source_location": "L53"}, {"caller_nid": "auth_login", "callee": "HTTPException", "source_file": "D:\\hms-project\\backend\\app\\api\\v1\\endpoints\\auth.py", "source_location": "L58"}, {"caller_nid": "auth_login", "callee": "create_access_token", "source_file": "D:\\hms-project\\backend\\app\\api\\v1\\endpoints\\auth.py", "source_location": "L65"}, {"caller_nid": "auth_login", "callee": "str", "source_file": "D:\\hms-project\\backend\\app\\api\\v1\\endpoints\\auth.py", "source_location": "L65"}, {"caller_nid": "auth_login", "callee": "info", "source_file": "D:\\hms-project\\backend\\app\\api\\v1\\endpoints\\auth.py", "source_location": "L66"}, {"caller_nid": "auth_login", "callee": "str", "source_file": "D:\\hms-project\\backend\\app\\api\\v1\\endpoints\\auth.py", "source_location": "L72"}, {"caller_nid": "auth_logout", "callee": "decode_token", "source_file": "D:\\hms-project\\backend\\app\\api\\v1\\endpoints\\auth.py", "source_location": "L87"}, {"caller_nid": "auth_logout", "callee": "HTTPException", "source_file": "D:\\hms-project\\backend\\app\\api\\v1\\endpoints\\auth.py", "source_location": "L89"}, {"caller_nid": "auth_logout", "callee": "get", "source_file": "D:\\hms-project\\backend\\app\\api\\v1\\endpoints\\auth.py", "source_location": "L91"}, {"caller_nid": "auth_logout", "callee": "get", "source_file": "D:\\hms-project\\backend\\app\\api\\v1\\endpoints\\auth.py", "source_location": "L92"}, {"caller_nid": "auth_logout", "callee": "fromtimestamp", "source_file": "D:\\hms-project\\backend\\app\\api\\v1\\endpoints\\auth.py", "source_location": "L96"}, {"caller_nid": "auth_logout", "callee": "first", "source_file": "D:\\hms-project\\backend\\app\\api\\v1\\endpoints\\auth.py", "source_location": "L99"}, {"caller_nid": "auth_logout", "callee": "filter", "source_file": "D:\\hms-project\\backend\\app\\api\\v1\\endpoints\\auth.py", "source_location": "L99"}, {"caller_nid": "auth_logout", "callee": "query", "source_file": "D:\\hms-project\\backend\\app\\api\\v1\\endpoints\\auth.py", "source_location": "L99"}, {"caller_nid": "auth_logout", "callee": "BlacklistedToken", "source_file": "D:\\hms-project\\backend\\app\\api\\v1\\endpoints\\auth.py", "source_location": "L101"}, {"caller_nid": "auth_logout", "callee": "add", "source_file": "D:\\hms-project\\backend\\app\\api\\v1\\endpoints\\auth.py", "source_location": "L102"}, {"caller_nid": "auth_logout", "callee": "commit", "source_file": "D:\\hms-project\\backend\\app\\api\\v1\\endpoints\\auth.py", "source_location": "L103"}, {"caller_nid": "auth_logout", "callee": "info", "source_file": "D:\\hms-project\\backend\\app\\api\\v1\\endpoints\\auth.py", "source_location": "L104"}, {"caller_nid": "auth_request_password_reset", "callee": "strip", "source_file": "D:\\hms-project\\backend\\app\\api\\v1\\endpoints\\auth.py", "source_location": "L122"}, {"caller_nid": "auth_request_password_reset", "callee": "lower", "source_file": "D:\\hms-project\\backend\\app\\api\\v1\\endpoints\\auth.py", "source_location": "L122"}, {"caller_nid": "auth_request_password_reset", "callee": "first", "source_file": "D:\\hms-project\\backend\\app\\api\\v1\\endpoints\\auth.py", "source_location": "L123"}, {"caller_nid": "auth_request_password_reset", "callee": "filter", "source_file": "D:\\hms-project\\backend\\app\\api\\v1\\endpoints\\auth.py", "source_location": "L123"}, {"caller_nid": "auth_request_password_reset", "callee": "query", "source_file": "D:\\hms-project\\backend\\app\\api\\v1\\endpoints\\auth.py", "source_location": "L123"}, {"caller_nid": "auth_request_password_reset", "callee": "get_blind_index", "source_file": "D:\\hms-project\\backend\\app\\api\\v1\\endpoints\\auth.py", "source_location": "L123"}, {"caller_nid": "auth_request_password_reset", "callee": "randint", "source_file": "D:\\hms-project\\backend\\app\\api\\v1\\endpoints\\auth.py", "source_location": "L128"}, {"caller_nid": "auth_request_password_reset", "callee": "update", "source_file": "D:\\hms-project\\backend\\app\\api\\v1\\endpoints\\auth.py", "source_location": "L131"}, {"caller_nid": "auth_request_password_reset", "callee": "filter", "source_file": "D:\\hms-project\\backend\\app\\api\\v1\\endpoints\\auth.py", "source_location": "L131"}, {"caller_nid": "auth_request_password_reset", "callee": "query", "source_file": "D:\\hms-project\\backend\\app\\api\\v1\\endpoints\\auth.py", "source_location": "L131"}, {"caller_nid": "auth_request_password_reset", "callee": "get_blind_index", "source_file": "D:\\hms-project\\backend\\app\\api\\v1\\endpoints\\auth.py", "source_location": "L132"}, {"caller_nid": "auth_request_password_reset", "callee": "now", "source_file": "D:\\hms-project\\backend\\app\\api\\v1\\endpoints\\auth.py", "source_location": "L137"}, {"caller_nid": "auth_request_password_reset", "callee": "timedelta", "source_file": "D:\\hms-project\\backend\\app\\api\\v1\\endpoints\\auth.py", "source_location": "L137"}, {"caller_nid": "auth_request_password_reset", "callee": "OTPRecord", "source_file": "D:\\hms-project\\backend\\app\\api\\v1\\endpoints\\auth.py", "source_location": "L138"}, {"caller_nid": "auth_request_password_reset", "callee": "add", "source_file": "D:\\hms-project\\backend\\app\\api\\v1\\endpoints\\auth.py", "source_location": "L144"}, {"caller_nid": "auth_request_password_reset", "callee": "commit", "source_file": "D:\\hms-project\\backend\\app\\api\\v1\\endpoints\\auth.py", "source_location": "L145"}, {"caller_nid": "auth_request_password_reset", "callee": "send_otp_email", "source_file": "D:\\hms-project\\backend\\app\\api\\v1\\endpoints\\auth.py", "source_location": "L147"}, {"caller_nid": "auth_confirm_password_reset", "callee": "strip", "source_file": "D:\\hms-project\\backend\\app\\api\\v1\\endpoints\\auth.py", "source_location": "L155"}, {"caller_nid": "auth_confirm_password_reset", "callee": "lower", "source_file": "D:\\hms-project\\backend\\app\\api\\v1\\endpoints\\auth.py", "source_location": "L155"}, {"caller_nid": "auth_confirm_password_reset", "callee": "now", "source_file": "D:\\hms-project\\backend\\app\\api\\v1\\endpoints\\auth.py", "source_location": "L156"}, {"caller_nid": "auth_confirm_password_reset", "callee": "first", "source_file": "D:\\hms-project\\backend\\app\\api\\v1\\endpoints\\auth.py", "source_location": "L158"}, {"caller_nid": "auth_confirm_password_reset", "callee": "filter", "source_file": "D:\\hms-project\\backend\\app\\api\\v1\\endpoints\\auth.py", "source_location": "L158"}, {"caller_nid": "auth_confirm_password_reset", "callee": "query", "source_file": "D:\\hms-project\\backend\\app\\api\\v1\\endpoints\\auth.py", "source_location": "L158"}, {"caller_nid": "auth_confirm_password_reset", "callee": "get_blind_index", "source_file": "D:\\hms-project\\backend\\app\\api\\v1\\endpoints\\auth.py", "source_location": "L159"}, {"caller_nid": "auth_confirm_password_reset", "callee": "HTTPException", "source_file": "D:\\hms-project\\backend\\app\\api\\v1\\endpoints\\auth.py", "source_location": "L167"}, {"caller_nid": "auth_confirm_password_reset", "callee": "first", "source_file": "D:\\hms-project\\backend\\app\\api\\v1\\endpoints\\auth.py", "source_location": "L169"}, {"caller_nid": "auth_confirm_password_reset", "callee": "filter", "source_file": "D:\\hms-project\\backend\\app\\api\\v1\\endpoints\\auth.py", "source_location": "L169"}, {"caller_nid": "auth_confirm_password_reset", "callee": "query", "source_file": "D:\\hms-project\\backend\\app\\api\\v1\\endpoints\\auth.py", "source_location": "L169"}, {"caller_nid": "auth_confirm_password_reset", "callee": "get_blind_index", "source_file": "D:\\hms-project\\backend\\app\\api\\v1\\endpoints\\auth.py", "source_location": "L169"}, {"caller_nid": "auth_confirm_password_reset", "callee": "HTTPException", "source_file": "D:\\hms-project\\backend\\app\\api\\v1\\endpoints\\auth.py", "source_location": "L171"}, {"caller_nid": "auth_confirm_password_reset", "callee": "hash_password", "source_file": "D:\\hms-project\\backend\\app\\api\\v1\\endpoints\\auth.py", "source_location": "L173"}, {"caller_nid": "auth_confirm_password_reset", "callee": "commit", "source_file": "D:\\hms-project\\backend\\app\\api\\v1\\endpoints\\auth.py", "source_location": "L175"}, {"caller_nid": "auth_confirm_password_reset", "callee": "info", "source_file": "D:\\hms-project\\backend\\app\\api\\v1\\endpoints\\auth.py", "source_location": "L177"}]}